cjfx/__init__.py
cjfx/cjfx.py
cjfx/excel.py
cjfx/mssql_connection.py
cjfx/sqlite_connection.py
cjfx/word.py
cjfx-0.0.2.dist-info/METADATA
cjfx-0.0.2.dist-info/WHEEL
cjfx-0.0.2.dist-info/top_level.txt
cjfx-0.0.2.dist-info/RECORD
