Metadata-Version: 2.1
Name: cjfx
Version: 0.0.2
Summary: A module for common functions optimised for data scientists that need to code repeatitive tasks fast
Home-page: https://github.com/celray/cjfx
Author: Celray James CHAWANDA
Author-email: celray@chawanda.com
Classifier: Development Status :: 3 - Alpha
Classifier: Intended Audience :: Developers
Classifier: License :: OSI Approved :: MIT License
Classifier: Programming Language :: Python :: 3.8
Classifier: Programming Language :: Python :: 3.9
Classifier: Programming Language :: Python :: 3.10
Classifier: Programming Language :: Python :: 3.11
Classifier: Programming Language :: Python :: 3.12
Requires-Dist: pytube
Requires-Dist: geopandas
Requires-Dist: matplotlib
Requires-Dist: numpy
Requires-Dist: pandas
Requires-Dist: psycopg2-binary
Requires-Dist: requests
Requires-Dist: rtree
Requires-Dist: seaborn
Requires-Dist: xarray
Requires-Dist: xlsxwriter
Requires-Dist: Pillow
Requires-Dist: pySmartDL
Requires-Dist: docxcompose
Requires-Dist: python-docx
Requires-Dist: tqdm
Requires-Dist: wget
Requires-Dist: rasterio
Requires-Dist: openpyxl
Requires-Dist: pyodbc
Requires-Dist: SQLAlchemy
Requires-Dist: pydub
Requires-Dist: shapely
